Metadata-Version: 2.1
Name: pyqt5-utils
Version: 1.0.4
Summary: Utilities for PyQt5
Home-page: UNKNOWN
Author: Hadi Hassan
Author-email: hassanhadi17@hotmail.com
License: UNKNOWN
Platform: UNKNOWN
Requires-Python: >=3.6
License-File: LICENSE
